<annotation><filename>00202_207.jpg</filename><folder>2018-1-16-9-20-55</folder><source><sourceImage>The MIT-CSAIL database of objects and scenes</sourceImage><sourceAnnotation>LabelMe Webtool</sourceAnnotation></source><object><name>bien_khac</name><deleted>1</deleted><verified>0</verified><occluded>no</occluded><attributes/><parts><hasparts/><ispartof/></parts><date>17-Jan-2018 05:04:52</date><id>0</id><type>bounding_box</type><polygon><username>mmlab</username><pt><x>1501</x><y>534</y></pt><pt><x>1618</x><y>534</y></pt><pt><x>1618</x><y>647</y></pt><pt><x>1501</x><y>647</y></pt></polygon></object><imagesize><nrows></nrows><ncols></ncols></imagesize></annotation>