<annotation><filename>MVI_1054_1.jpg</filename><folder>2018-1-16-9-20-55</folder><source><sourceImage>The MIT-CSAIL database of objects and scenes</sourceImage><sourceAnnotation>LabelMe Webtool</sourceAnnotation></source><object><name>re_phai</name><deleted>1</deleted><verified>0</verified><occluded>no</occluded><attributes/><parts><hasparts/><ispartof/></parts><date>16-Jan-2018 10:09:45</date><id>0</id><type>bounding_box</type><polygon><username>mmlab</username><pt><x>402</x><y>130</y></pt><pt><x>435</x><y>130</y></pt><pt><x>435</x><y>165</y></pt><pt><x>402</x><y>165</y></pt></polygon></object><object><name>re_phai</name><deleted>1</deleted><verified>0</verified><occluded>no</occluded><attributes/><parts><hasparts/><ispartof/></parts><date>16-Jan-2018 10:10:09</date><id>1</id><type>bounding_box</type><polygon><username>mmlab</username><pt><x>395</x><y>116</y></pt><pt><x>421</x><y>116</y></pt><pt><x>421</x><y>130</y></pt><pt><x>395</x><y>130</y></pt></polygon></object><object><name>re_phai</name><deleted>0</deleted><verified>0</verified><occluded>no</occluded><attributes/><parts><hasparts/><ispartof/></parts><date>16-Jan-2018 10:10:46</date><id>2</id><type>bounding_box</type><polygon><username>mmlab</username><pt><x>406</x><y>133</y></pt><pt><x>432</x><y>133</y></pt><pt><x>432</x><y>164</y></pt><pt><x>406</x><y>164</y></pt></polygon></object><object><name>cam_re_trai</name><deleted>1</deleted><verified>0</verified><occluded>no</occluded><attributes/><parts><hasparts/><ispartof/></parts><date>16-Jan-2018 10:11:01</date><id>3</id><type>bounding_box</type><polygon><username>mmlab</username><pt><x>231</x><y>118</y></pt><pt><x>245</x><y>118</y></pt><pt><x>245</x><y>132</y></pt><pt><x>231</x><y>132</y></pt></polygon></object><object><name>re_phai</name><deleted>1</deleted><verified>0</verified><occluded>no</occluded><attributes/><parts><hasparts/><ispartof/></parts><date>16-Jan-2018 10:17:22</date><id>4</id><type>bounding_box</type><polygon><username>mmlab</username><pt><x>400</x><y>116</y></pt><pt><x>414</x><y>116</y></pt><pt><x>414</x><y>128</y></pt><pt><x>400</x><y>128</y></pt></polygon></object><imagesize><nrows></nrows><ncols></ncols></imagesize><object><name>asd</name><deleted>1</deleted><verified>0</verified><occluded>no</occluded><attributes>l__</attributes><parts><hasparts/><ispartof/></parts><date>17-Jan-2018 02:00:32</date><id>5</id><type>bounding_box</type><polygon><username>anonymous</username><pt><x>303</x><y>160</y></pt><pt><x>335</x><y>160</y></pt><pt><x>335</x><y>192</y></pt><pt><x>303</x><y>192</y></pt></polygon></object></annotation>